prlps_logger/__init__.py
prlps_logger-0.0.3.dist-info/METADATA
prlps_logger-0.0.3.dist-info/WHEEL
prlps_logger-0.0.3.dist-info/top_level.txt
prlps_logger-0.0.3.dist-info/RECORD
