Metadata-Version: 2.2
Name: prlps_logger
Version: 0.0.3
Summary: простой пример логгера для записи логов в файл и вывода в консоль, или в html для HTMLResponse FastAPI
Home-page: https://github.com/gniloyprolaps/prlps_logger
Author: prolapser
License: LICENSE.txt
Classifier: Development Status :: 4 - Beta
Classifier: Intended Audience :: Developers
Classifier: License :: OSI Approved :: MIT License
Classifier: Operating System :: OS Independent
Classifier: Programming Language :: Python :: 3.6
Classifier: Topic :: Education :: Testing
Classifier: Topic :: Software Development :: Testing
Classifier: Topic :: System :: Logging
Requires-Python: >=3.6
Dynamic: author
Dynamic: classifier
Dynamic: description
Dynamic: description-content-type
Dynamic: home-page
Dynamic: license
Dynamic: requires-python
Dynamic: summary
